sentimentanalyser/__init__.py
sentimentanalyser/model_test.py
sentimentanalyser/model_train.py
sentimentanalyser/preprocess.py
sentimentanalyser-2.5.dist-info/LICENSE.rst
sentimentanalyser-2.5.dist-info/METADATA
sentimentanalyser-2.5.dist-info/WHEEL
sentimentanalyser-2.5.dist-info/top_level.txt
sentimentanalyser-2.5.dist-info/RECORD
