Metadata-Version: 2.1
Name: sentimentanalyser
Version: 2.5
Summary: Generic python library to perform sentiment analysis on any dataset, using different models
Home-page: UNKNOWN
Author: Sanjay Pradeep,Jayanth Anantharapu, Aditya Kumar, Ashhadul Islam
Author-email: sanjay.sndk@gmail.com, aditya00kumar@gmail.com, ashhadulislam@gmail.com
License: MIT
Keywords: Classification,Binary Classification,Multi-label Classification,Text data
Platform: UNKNOWN
Requires-Dist: nltk
Requires-Dist: numpy
Requires-Dist: openpyxl
Requires-Dist: pandas
Requires-Dist: scikit-learn
Requires-Dist: scipy
Requires-Dist: six
Requires-Dist: tqdm
